lurlene/__init__.py
lurlene/api.py
lurlene/bridge.py
lurlene/context.py
lurlene/model.py
lurlene/osc.py
lurlene/parse.py
lurlene/pitch.py
lurlene/scale.py
lurlene/transform.py
lurlene/util.py
lurlene/xtra.py
Lurlene-21.dist-info/COPYING
Lurlene-21.dist-info/METADATA
Lurlene-21.dist-info/WHEEL
Lurlene-21.dist-info/top_level.txt
Lurlene-21.dist-info/RECORD
