Metadata-Version: 2.1
Name: Lurlene
Version: 21
Summary: Python-based live-coding language optimised for a small number of channels
Home-page: https://github.com/combatopera/Lurlene
Author: Andrzej Cichocki
Author-email: 3613868+combatopera@users.noreply.github.com
License-File: COPYING
Requires-Dist: diapyr>=18
Requires-Dist: foyndation>=12
Requires-Dist: numpy>=2.0.2
Requires-Dist: splut>=4
Requires-Dist: timelyOSC>=4
